[
    {
        "tab": 1,
        "data": [
            {
                "id": 0,
                "name": "คอนโดมีเนียม",
                "brands": [
                    {
                        "name": "ดิ เอส",
                        "link": "#",
                        "location": [
                            {
                                "name": "ดิ เอส แอด สิงห์ คอมเพล็กซ์",
                                "label": "new_project",
                                "date": "14 JULY 2023",
                                "price": "STARTS 500 MB",
                                "link": "#"
                            },
                            {
                                "name": "ดิ เอส สุขุมวิท 36",
                                "label": "new_project",
                                "date": "14 JULY 2023",
                                "price": "STARTS 500 MB",
                                "link": "#"
                            },
                            {
                                "name": "ดิ เอส อโศก",
                                "label": "new_project",
                                "date": "14 JULY 2023",
                                "price": "STARTS 500 MB",
                                "link": "#"
                            }
                        ]
                    },
                    {
                        "name": "ดิ เอ็กซ์โทร",
                        "link": "#",
                        "location": [
                            {
                                "name": "ดิ เอ็กซ์โทร พญาไท-รางน้ำ",
                                "label": "new_project",
                                "date": "14 JULY 2023",
                                "price": "STARTS 500 MB",
                                "link": "#"
                            }
                        ]
                    }
                ]
            }
        ]
    },
    {
        "tab": 2,
        "data": [
            {
                "name": "บ้านเดี่ยว",
                "brands": [
                    {
                        "name": "สันติบุรี เดอะ เรสซิเดนเซส",
                        "link": "#",
                        "location": [
                            {
                                "name": "สันติบุรี เดอะ เรสซิเดนเซส",
                                "label": "new_project",
                                "date": "14 JULY 2023",
                                "price": "STARTS 500 MB",
                                "link": "#"
                            }
                        ]
                    },
                    {
                        "name": "ศิรนินทร์ เรสซิเดนเซส",
                        "link": "#",
                        "location": [
                            {
                                "name": "ศิรนินทร์ เรสซิเดนเซส พัฒนาการ",
                                "label": "new_project",
                                "date": "14 JULY 2023",
                                "price": "STARTS 500 MB",
                                "link": "#"
                            }
                        ]
                    },
                    {
                        "name": "สริน",
                        "link": "#",
                        "location": [
                            {
                                "name": "สริน ราชพฤกษ์ สาย 1",
                                "label": "new_project",
                                "date": "14 JULY 2023",
                                "price": "STARTS 500 MB",
                                "link": "#"
                            }
                        ]
                    },
                    {
                        "name": "ณอน",
                        "link": "#",
                        "location": [
                            {
                                "name": "ณอน ปัญญาอินทรา",
                                "label": "new_project",
                                "date": "14 JULY 2023",
                                "price": "STARTS 500 MB",
                                "link": "#"
                            },
                            {
                                "name": "ณอน วงแหวน-จตุโชติ",
                                "label": "new_project",
                                "date": "14 JULY 2023",
                                "price": "STARTS 500 MB",
                                "link": "#"
                            }
                        ]
                    }
                ]
            },
            {
                "name": "ไพรเวท เอสเตท",
                "brands": [
                    {
                        "name": "",
                        "link": "#",
                        "location": [
                            {
                                "name": "ลาชัวว์ เดอ เอส สุขุมวิท 43",
                                "label": "new_project",
                                "date": "14 JULY 2023",
                                "price": "STARTS 500 MB",
                                "link": "#"
                            }
                        ]
                    },
                    {
                        "name": "",
                        "link": "#",
                        "location": [
                            {
                                "name": "สมิทธ์ รามอินทรา",
                                "label": "new_project",
                                "date": "14 JULY 2023",
                                "price": "STARTS 500 MB",
                                "link": "#"
                            }
                        ]
                    }
                ]
            },
            {
                "name": "โฮม ออฟฟิศ",
                "brands": [
                    {
                        "name": "",
                        "link": "#",
                        "location": [
                            {
                                "name": "เซนเทอร์ พัฒนาการ",
                                "label": "new_project",
                                "date": "14 JULY 2023",
                                "price": "STARTS 500 MB",
                                "link": "#"
                            }
                        ]
                    }
                ]
            }
        ]
    },
    {
        "tab": 3,
        "data": [
            {
                "name": "",
                "brands": [
                    {
                        "name": "รวมโครงการจากสิงห์เอสเตท",
                        "link": "#"
                    },
                    {
                        "name": "เรื่องราวจากสิงห์เอสเตท",
                        "link": "#"
                    },
                    {
                        "name": "ข่าวสารและกิจกรรม",
                        "link": "#"
                    },
                    {
                        "name": "ประกาศความเป็นส่วนตัว",
                        "link": "#"
                    },
                    {
                        "name": "เกี่ยวกับสิงห์เอสเตท",
                        "link": "#"
                    },
                    {
                        "name": "การพัฒนาที่ยั่งยืน",
                        "link": "#"
                    },
                    {
                        "name": "นักลงทุนสัมพันธ์",
                        "link": "#"
                    },
                    {
                        "name": "ติดต่อเรา",
                        "link": "#"
                    },
                    {
                        "name": "สมัครตัวแทนขายโครงการ",
                        "link": "#"
                    }
                ]
            }
        ]
    }
]